cars/__init__.py
cars/base_car.py
cars/fancy_car.py
cars/fast_car.py
cars/slow_car.py
irl_master_project_assessment-0.0.1.dist-info/METADATA
irl_master_project_assessment-0.0.1.dist-info/WHEEL
irl_master_project_assessment-0.0.1.dist-info/top_level.txt
irl_master_project_assessment-0.0.1.dist-info/RECORD
